{"songs": [{"title": "Like I Do", "album": "Liberation", "year": "2018-06-07", "lyrics": "[Verse 1: GoldLink]\nRight, heaviest heaven, talk to the reverend\nBut I know you bad as fuck and I'm tryna fuck\nAnd you know we perfect baby girl, look at us\nMake a young nigga cash out and run it up\nAll that little booty in your trunk\nMake a man wanna say hallelujah when they jump\nMake 'em buy a little Porsche, I'm around you so we stunt\nBlack men, black car, let you buy you what you want, uh\nNo, wait, baby you a problem\nSagittarius, hmm, exciting\nLink and Aguilera, so you know we're gossip\nCoexistence, you the moon, I'm the sun\nGenie in my bottle, I'm trying to rub on your hips\nAin't no other man who can talk to you like I did, that's real\nLet's start a family, I'm Uncle Phil, you my Aunt Viv\nFly to Spain, go to Rome\nWe don't ever have to ever go home\nI wanna love you from your head to your toe\nI like a little fuss and fighting when I go\nYou say leave, tell me stay, want me go\nThen I leave, pump fake like I'm gone\nBut you know I never leave you on your own\nAnd you're too bad for these brothers who be on your phone like\n\n[Verse 2: Christina Aguilera]\nLet me make this simple for ya\nLay it out on the table for ya\nIn case you need a little reminder\nI've been doing this way before you\nBoy, you already know my story\nYou were raised in all my glory\n\n[Pre-Chorus: Christina Aguilera]\nI don't need your little money\nI can put you under something\nStop talking, we can get along\nWe can Marvin Gaye and get it on\nWhere you want to be, I've been before\nShh, say no more\nBoy, you're so much better when you don't speak\nIf you get somethin',  get one thing\nCan't play me, boy, I'm out of your league\n\n[Chorus: Christina Aguilera & GoldLink]\nNo, baby, you can't do it quite like I do\nI do\nLike I do\nI may not want, but just might have to show you\nShow you\nWhat I do\nAnd you can't do it quite like I do\n\n[Verse 3: Christina Aguilera]\nThis feeling is legendary\nWelcome to my sanctuary\nEvery time like the first time\nBut, baby, girls like me ain't temporary\nCan't fake it when it comes this natural\nI ain't ever tried, it's just natural, ha\n\n[Pre-Chorus: Christina Aguilera]\nI don't need your little money\nI can put you under something\nStop talking, we can get along\nWe can Marvin Gaye and get it on\nWhere you wanna be, I've been before\nShh, say no more\nBoy, you're so much better when you don't speak\nIf you get somethin' get one thing\nCan't play me, boy, I'm out of your league\n\n[Chorus: Christina Aguilera & GoldLink]\nNo, baby, you can't do it quite like I do\nI do\nLike I do\nI may not want, but just might have to show you\nShow you\nWhat I do\nAnd you can't do it quite like I do\n\n[Bridge A: Christina Aguilera]\nOooh (Oooh)\nCan't keep running your mouth (Can't keep running your mouth)\nI got time but (Got time now)\nWhat I gotta lie, what I gotta lie about? (What I gotta lie about?)\nOooh\nThere you go running your mouth (There you go, running your mouth)\nShow me what it is\nShow me right now (Show me what it is, show me right now)\n'Cause I can do (Oh, oh)\n\n[Bridge B: Christina Aguilera & GoldLink]\nDon't talk for a second\nJust get all this lesson\nDon't you second guess it\nJust show some respect and\nIt can go far for you\nI know it's kind of hard for you\nIt's not my job, but you're working so hard\nI can share a bar or two\nPlus you're kinda cute\n\n[Pre-Chorus: Christina Aguilera]\nStop talking, we can get along\nWe can Marvin Gaye and get it on\nWhere you wanna be, I've been before\nShh, say no more (say no more)\nBoy, you're so much better when you don't speak\nIf you get somethin', get one thing\nCan't play me, boy, I'm out of your league\n\n[Chorus: Christina Aguilera & GoldLink]\nNo, baby, you can't do it quite like I do (Woo)\nI do (Yeah)\nLike I do (Like I do)\nI may not want, but just might have to\nShow you (Let me show you what I do now, baby)\nShow you (Can't do it, boy, like I do, yeah, yeah)\nWhat I do (Yeah)\nAnd you can't do it quite like I do (Woo)\n\n[Outro: Christina Aguilera]\nHahaha\nHey\nUh\nYeah\nHey yeah\nOh\nOooh\nYeah, yeah, yeah\nWooo", "image": "https://images.genius.com/3cb43fc68ca5ee26baf04becf7b37cc5.1000x1000x1.jpg"}], "artist": "Christina Aguilera"}