{"songs": [{"title": "The Happiest Girl In The Whole U.S.A.", "album": null, "year": "2009-02-03", "lyrics": "Shine on me sunshine\nWalk with me world\nIt's a skip-a-dee-doo-dah day\nI'm the happiest girl in the whole U.S.A\n\nGood morning, morning, hello sunshine\nWake up sleepy head\nWhy'd we move on that bojangle clock\nSo far away from the bed?\n\nJust one more minute, that's why we moved it\nOne more hug or two\nDo you love wakin' up next to me\nAs much as I love wakin' up next to you?\n\nWell you make the coffee and I'll make the bed\nI'll fix your lunch and you'll fix mine\nNow tell me the truth, do these old shoes look funny?\nHoney, it's almost nine\n\nNow you be careful, gotta go\nI love you, have a beautiful day\nAnd kiss the happiest girl in the whole U.S.A\n\nSkip-a-dee-doo-dah\nThank you Lord for making him for me\nAnd thank you for making life turn out\nThe way I always thought it should be\n\nThere once was a time when I could not imagine\nHow it would feel to say\nI'm the happiest girl in the whole U.S.A\n\nShine on me sunshine\nWalk with me world\nIt's a skip-a-dee-doo-dah day\nI'm the happiest girl in the whole U.S.A", "image": "https://images.genius.com/48fbb4785830a66d5ed308f5f31ec68f.500x500x1.jpg"}], "artist": "Lana Del Rey"}