{"songs": [{"title": "Fine China", "album": null, "year": "2016-12-25", "lyrics": "[Verse 1]\nI wore diamonds for the birth of your baby\nFor the birth of your son\nOn the same day, my husband-to-be\nPacked his things to run\nWas bittersweet to say the least\nOne life begins, one comes undone\nI've always been a strong woman of faith\nStrong like a tree, but the unlucky one\n\n[Pre-Chorus]\nI'm going down now\nWith all of my\n\n[Chorus]\nFine china and fresh linen\nAll of my dresses with them tags still on them\nFine china and dull silver\nMy white horses and my ivory almonds\nI guess they really got the best of us, didn't they?\nThey said that love was enough, but it wasn't\nThe Earth shattered, the sky opened\nThe rain was fire, but we were wooden\n\n[Verse 2]\nI wore diamonds for the day of our wedding\nFor our day in the sun\nOn the same day, my mother-to-be said she wouldn't come\nIt's always been that way with me\nNo time for change, no time for fun\nIt's always been that way, it seems\nOne love begins, one comes undone\n\n[Pre-Chorus]\nI'm going down now\nWith all of my\n\n[Chorus]\nFine china and fresh linen\nAll of my dresses with them tags still on them\nFine china and dull silver\nMy white horses and my ivory almonds\nI guess they really got the best of us, didn't they?\nThey said that love was enough, but it wasn't\nThe Earth shattered, the sky opened\nThe rain was fire, but we were wooden\n\n[Bridge]\nAll of my, all of my fine china\nAll of my, all of my fine china\nAll of my, all of my fine china\nBlue, ah, blue\nAll of my, all of my fine china\nAll of my, all of my fine china\nAll of my, all of my fine china\nBlue, ah\n\n[Chorus]\nFine china and fresh linen\nAll of my dresses with them tags still on them\nFine china and dull silver\nMy white horses and my ivory almonds\nI guess they really got the best of us, didn't they?\nThey said that love was enough, but it wasn't\nThe Earth shattered, the sky opened\nThe rain was fire, but we were wooden\n\n[Outro]\nFine china, fine china, fine china\nFresh linen, fresh linen, fresh linen\nAh, ah, ah, ah, ah, ah\nAh, ah, ah, ah, ah, ah\nAh, ah, ah, ah, ah, ah\nAh, ah, ah, ah, ah, ah\nAh, ah, ah, ah, ah, ah\nAh, ah, ah, ah, ah, ah\n\nAh, ah, ah, ah, ah, ah\nAh, ah, ah, ah, ah, ah\nAh, ah, ah, ah, ah, ah\nAh, ah, ah, ah, ah, ah\nAh, ah, ah, ah, ah, ah\nAh, ah, ah, ah, ah, ah", "image": "https://images.genius.com/e5aeebea8593e83f7d81caa1bf67b118.1000x1000x1.jpg"}], "artist": "Lana Del Rey"}