{"songs": [{"title": "Touch", "album": "TRXYE - EP", "year": "2014-08-15", "lyrics": "[Verse 1]\nGlow is low and it's dimming\nAnd the silence is ringing\nI can almost feel your breath\nI can almost feel the rest\nNight is young and we're living\nHands move, moving steady\nThe time's moving slower\nI can feel we're getting closer, closer, yeah\n\n[Chorus]\nStanding in the eye of the storm\nMy eyes start to roam to the curl of your lips\nAnd the center of eclipse\nIn total darkness I reach out and touch\n\n[Verse 2]\nMy mind's gone a-racing\nOn a horse that's escaping\nAnd I'm ready to jump, yeah I'm ready to swim\nLife is chances that are taken\nBut nothing's ever broken\nThey're just pieces on the ground\nYour hands need to build them\nMy mind\u2019s gone running\nMy hands cut loose\nBut there's no need for answers\nJust the things you gotta do\n\n[Bridge]\nAnd I need you to trust the lust\nWe must get past all these rules\nWe must choose to reach out and, touch\n\n[Chorus]\nStanding in the eye of the storm\nMy eyes start to roam to the curl of your lips\nAnd the center of eclipse\nIn total darkness I reach out and\nStanding in the eye of the storm\nMy eyes start to roam to the curl of your lips\nAnd the center of eclipse\nIn total darkness I reach, I reach out and touch", "image": "https://images.genius.com/41e3c4e3f9c3d9b1a6a3f7c9f3cbea7e.1000x1000x1.jpg"}], "artist": "Troye Sivan"}