{"songs": [{"title": "COOL", "album": "Blue Neighbourhood (Deluxe)", "year": "2015-12-04", "lyrics": "[Verse 1]\nSweet life living\nPools and swimming\nDrinks in bars and\nBoys in cars and\nRooftop sinning\nSkinny dipping\nShooting stars with you\nFat cigars and\n\n[Pre-Chorus]\nAnd that weekend up in the islands\nThey stop and stare\nFlashes filling the silence\nOf a Hollywood love affair\nWaking up in the islands\nCause I saw you there\nLost and trying to be\n\n[Chorus]\nI was just trying to be cool\nI was just trying to be like you\nI'm a spark and you're a boom\nWhat am I supposed to do?\n\n[Verse 2]\nMansion debut\nLove it, do you?\nAbsent father\nPays his daughter\nAnd her mama withdrew\nFrom the life they once knew\nShe had a heart\nBut she sold it off for\n\n[Pre-Chorus]\nAnd that weekend up in the islands\nThey stop and stare\nFlashes filling the silence\nOf a Hollywood love affair\nWaking up in the islands\nCause I saw you there\nLost and trying to be\n\n[Chorus]\nI was just trying to be cool\nI was just trying to be like you\nI'm a spark and you're a boom\nWhat am I supposed to do?\n\n[Post-Chorus]\nWhen I've got that cigarette smoke\nAnd Saint Laurent coat, but nothing is feeling right\nI drink but I choke\nI love but I don't\n\n[Chorus]\nI was just trying to be cool\nI was just trying to be like you\nI was just trying to be cool\nI was just trying to be like you\nI'm a spark and you're a boom\nWhat am I supposed to do?\n\n[Post-Chorus]\nWhen I've got that cigarette smoke\nAnd Saint Laurent coat, but nothing is feeling right\nI drink but I choke\nI love but I don't, yeah\n\n[Chorus]\nI was just trying to be cool\nI was just trying to be like you", "image": "https://images.genius.com/cc42c0f3b0d4f3fda2f9a07a60b9ce9a.630x630x1.jpg"}], "artist": "Troye Sivan"}