{"songs": [{"title": "TALK ME DOWN", "album": "Blue Neighbourhood (Deluxe)", "year": "2015-10-13", "lyrics": "[Verse 1]\nI wanna sleep next to you\nBut that's all I wanna do right now\nAnd I wanna come home to you\nBut home is just a room full of my safest sounds\n'Cause you know that I can't trust myself with my 3AM shadow\nI'd rather fuel a fantasy than deal with this alone\n\n[Chorus]\nI wanna sleep next to you\nBut that's all I wanna do right now\nSo come over now and talk me down\n\n[Verse 2]\nI wanna hold hands with you\nBut that's all I wanna do right now\nAnd I wanna get close to you\n'Cause your hands and lips still know their way around\nAnd I know I like to draw the line when it starts to get too real\nBut the less time that I spend with you, the less you need to heal\n\n[Chorus]\nI wanna sleep next to you\nBut that's all I wanna do right now\nSo come over now and talk me down\n(Talk me down)\n\n[Bridge]\nSo if you don't mind, I'll walk that line\nStuck on the bridge between us\nGray areas and expectations\nBut I'm not the one if we're honest, yeah\nBut I wanna sleep next to you\nAnd I wanna come home to you\nI wanna hold hands with you\nI wanna be close to you\n\n[Outro]\nBut I wanna sleep next to you\nAnd that's all I wanna do right now\nAnd I wanna come home to you\nBut home is just a room full of my safest sounds\nSo come over now and talk me down\n(Talk me down)", "image": "https://images.genius.com/cc42c0f3b0d4f3fda2f9a07a60b9ce9a.630x630x1.jpg"}], "artist": "Troye Sivan"}