{"songs": [{"title": "I Kissed a Girl (Dr. Luke & Benny Blanco Remix)", "album": "The Hello Katy Australian Tour EP", "year": "2009-08-07", "lyrics": "[Intro]\nIt felt so wrong, it felt so right\nDon't mean I'm in love tonight\nI kissed a girl (girl, girl, girl...)\nI kissed a girl (girl, girl, girl...)\n\n[Drop 1]\nKiss...\nI kissed a (girl, girl, girl...)\nI kissed a (girl, girl, girl...)\n\n[Break]\n(Kiss, kiss, kiss, kiss...)\n\n[Drop 2]\nI kissed a girl, I kissed a girl just to\nI kissed a girl, I kissed a girl just to\nIt felt so wrong, it felt so right\nDon't mean I'm in love tonight\n(Night, night, night, night...)\n\n[Drop 3]\nKiss...\nI kissed a girl\n(Ki-ki-ki-ki-ki-ki...)\n(Girls, girls, girls, girls...)\nI kissed a girl, I kissed a girl, I kissed a girl\n(Ki-ki-ki-ki-ki-ki...)\n\n[Outro]\nKiss...\nKiss...\nKiss...\nKiss....", "image": "https://images.genius.com/81bbf1dfe455875d03a38e2cf7f7bd27.1000x1000x1.jpg"}], "artist": "Katy Perry"}