{"songs": [{"title": "Supermodel", "album": null, "year": "2016-11-18", "lyrics": "[Chorus: Justin Bieber]\nYou could be my supermodel\nYou could be my supermodel\nYou could be my supermodel\nOh, the way you strut your shit\nYou could be my supermodel (supermodel)\nOoh, I wanna take your pic\n\n[Verse 1: Justin Bieber]\nOh, it's like 3 in the morning\nAnd you see me lookin' at you\nOoh, I just can't control it\nCome over here so I can see you better\nI don't want you to leave\nBaby, you and me should be together\nSpend the night with me, yeah\n\n[Pre-Chorus: Justin Bieber]\nI'm talkin' 'bout first class treatment babe\nStartin' this evening baby\nTell me what you need and I'll pay\nEven though I know that you don't need anything\nI'm talkin' 'bout first class treatment babe\nStartin' this evening baby\nTell me what you need and I'll pay\nEven though I know that you don't need anything\n\n[Chorus: Justin Bieber]\nYou could be my supermodel\nThe way you strut your shit\nYou could be my supermodel\nOoh, I wanna take your pic\n\n[Verse 2: Justin Bieber]\nI could pick you up in a Rolls Royce\nAnywhere you wanna go, it's your choice\nI promise that I'm nothing like them other boys\nSoundz drop that beat just to make noise\nJust to make noise\nSoundz drop that beat just to make noise\nJust to make noise\nSoundz drop that beat just to make noise\n\n[Pre-Chorus: Justin Bieber]\nI'm talking bout first class treatment babe\nStarting this evening baby\nTell me what you need and I'll pay\nEven though I know that you don't need anything\nI'm talking bout first class treatment babe\nStarting this evening baby\nTell me what you need and I'll pay\nEven though I know that you don't need anything\n\n[Chorus: Justin Bieber]\nYou could be my supermodel\nThe way you strut your shit\nYou could be my supermodel\nOoh I wanna take your pic\n\n[Verse 3: Tyga]\nPretty I mean pretty exactly where I'm from\nYou still with me?\nI'm your new bad boy ball no biggie\n\nPop it on the collar\nI just pull up and park like play grounding\nBet you do anything for a one nighter\nBet I can make your friend freak like cirque du soleil...", "image": "https://images.genius.com/eb194c32ad750a40655f11685385d649.400x400x1.jpg"}], "artist": "Justin Bieber"}