{"songs": [{"title": "Torn Apart", "album": "Vs. (Other People\u2019s Heartache Pt. III)", "year": "2014-11-21", "lyrics": "[Verse 1]\nI could only be myself with you around\nOh, with you around\nBut now there's nothing left for me to think about\nOh, to think about\n\n[Pre-Chorus]\nAnd it hurts like hell to be torn apart\nAnd it hurts like hell to be thrown around\n\n[Chorus]\nWe were born to be together\nTorn apart, torn apart\nWe were born to be together\nTorn apart, torn apart\n\n[Verse 2]\nYou stamped with a heavy tread and left your mark\nOh, your mark on me\nThe space you used to fill is now this great black hole\nOh, you're out of sight but not out of mind\n\n[Pre-Chorus]\nAnd it hurts like hell to be torn apart\nAnd it hurts like hell to be thrown around\n\n[Chorus]\nWe were born to be together\nTorn apart, torn apart\nWe were born to be together\nTorn apart, torn apart\n\n[Interlude]\n\n[Chorus]\nWe were born to be together\nTorn apart, torn apart\nWe were born to be together\nTorn apart, torn apart\nWe were born to be together\nTorn apart, torn apart\nWe were born to be together\nTorn apart, torn apart", "image": "https://i.genius.com/77bf33b4916b9989d64dedf3f51157a2682f0216?url=http%3A%2F%2Fvignette3.wikia.nocookie.net%2Fbastille%2Fimages%2F6%2F69%2FBastille-torn-apart-cover.jpg%2Frevision%2Flatest%3Fcb%3D20150116202157"}], "artist": "Bastille"}