{"songs": [{"title": "Look What I Found", "album": "A Star is Born (Original Motion Picture Soundtrack)", "year": "2018-10-05", "lyrics": "[Intro]\n1-2-3\n\n[Verse 1]\nI'm alone in my house\nI'm out on the town\nI'm at the bottom of the bottle\nI've been knockin' 'em down\n\n[Pre-Chorus 1]\nI can't get back up on my feet\nSee the lights on the street like stars\n\n[Chorus 1]\nBut look what I found\nLook what I found\nAnother piece of my heart\nJust layin' on the ground\n\n[Verse 2]\nUnder the foggy day\nI\u2019m lookin' for a light\nAnd my only friend\nIs workin' tonight\n\n[Pre-Chorus 2]\nI can\u2019t get myself out of bed\nHear these voices in my head like a song\n\n[Chorus 2]\nBut look what I found\nSomebody who loves me\nLook what I found\nSomebody who'll carry 'round a piece of my heart\nJust layin' on the ground\n\n[Bridge]\nWhen I met you I was blown to pieces\nHeart all over the floor\nEver since you put me back together\nI can\u2019t believe it won\u2019t believe it\nUh\n\n[Chorus 3]\nLook what you found!\nYeah baby\nLook what I found\nSomeone who'll carry 'round a piece of my heart\nLook what I found\nWhoo!\nC'mon!\nLook what I found\nSomebody who loves me\nLook what we found\nSomebody who'll carry 'round a piece of my heart\nHeart just layin' on the ground", "image": "https://images.genius.com/3f750a8c9ce9268f9744c9fd99678824.867x867x1.png"}], "artist": "Lady Gaga"}