{"songs": [{"title": "Does It  Feel", "album": "Nine Track Mind (Deluxe)", "year": "2016-11-11", "lyrics": "[Verse 1]\nTell me lies, like how you're better off without me\nWhile the truth is written all over your face\nEven in photographs together, you look lonely, lonely\nWhen you were here, you never had to fake\n\n[Pre-Chorus]\nAnd girl, I promise I'm not gonna bother you anymore\nSoon as you hang up the phone\nI just got one question that you might not be ready for\nBut I really gotta know\n\n[Chorus]\nDoes it feel, feel like you never gon' find nothing better?\nDoes it feel, feel like you're missing, 'cause I loved you different?\n\n[Verse 2]\nAnd the way that you can say you don't remember\nHow I kept you coming over every night\nAnd the way that you can say you never wondered, wondered\nIf loving someone else is just a lie\n\n[Pre-Chorus]\nWhoa, girl, I promise I'm not gonna bother you anymore\nSoon as you hang up the phone\nI just got one question that you might not be ready for\nBut I really gotta know\n\n[Chorus]\nDoes it feel, feel like you never gon' find nothing better?\nDoes it feel, feel like you're missing, 'cause I loved you different?\nDoes it feel, feel like you never gon' find nothing better?\nDoes it feel, feel like you're missing, 'cause I loved you different?\n\n[Bridge]\nGirl, I promise I'm not gonna bother you anymore\nSoon as you hang up the phone\nI just got one question that you might not be ready for\nBut I really gotta know\n\n[Chorus]\nDoes it feel, feel like you never gon' find nothing better?\nDoes it feel, feel like you're missing, 'cause I loved you different?\nDoes it feel, feel like you never gon' find nothing better?\nDoes it feel, feel like you're missing, 'cause I loved you different?", "image": "https://images.genius.com/b4aefa5d186bbfd3c06960ac356041bf.1000x1000x1.jpg"}], "artist": "Charlie Puth"}