{"songs": [{"title": "Get Back (Live)", "album": "iTunes Live from London EP", "year": "2009-01-01", "lyrics": "[Intro: Demi Lovato]\nPut your hands together!\n\n[Verse 1: Demi Lovato]\nDon't walk away like you always do, this time\nBaby, you're the only thing that's been on my mind\nEver since you left, I've been a mess\nYou won't answer your phone\nI'll say it once, and I'll leave you alone, but I gotta let you know\n\n[Chorus: Demi Lovato]\nI wanna get back to the old days\nWhen the phone would ring and I knew it was you\nI wanna talk back and get yelled at\nFight for nothing, like we used to\nOh, kiss me like you mean it, like you miss me\nCause I know that you do\nI wanna get back, get back with you\n\n[Verse 2: Demi Lovato]\nDon't look at me that way, I see it in your eyes\nDon't worry about me, I've been fine\nI'm not gonna lie, I've been a mess since you've left\nAnd every time I see you, it gets more and more intense\n\n[Chorus: Demi Lovato]\nI wanna get back to the old days\nWhen the phone would ring and I knew it was you\nI wanna talk back and get yelled at\nFight for nothing, like we used to\nOh, kiss me like you mean it, like you miss me\nCause I know that you do\nI wanna get back, get back with you\n\n[Bridge: Demi Lovato]\nYou were the only one I wanted\nYou were the first one I fell for\nYou're the only one that I'm in need of\nAnd I don't want to be lonely anymore\n\n[Chorus: Demi Lovato]\nI wanna get back to the old days\nWhen the phone would ring and I knew it was you\nI wanna talk back and get yelled at\nFight for nothing, like we used to\nOh, kiss me like you mean it, like you miss me\nCause I know that you do\nI wanna get back, get back with you\n\n[Breakdown: Demi Lovato]\n(Get back!) Get Back!\nC'mon, sing it!\n(Get back!) Get Back!\n(Get back!) Get Back!\n(Get back!) Get Back!\n\n[Chorus - Shortened: Demi Lovato]\nOh, kiss me like you mean it, like you miss me\nCause I know that you do\n\n[Outro: Demi Lovato]\nI wanna get back, get back\nI wanna get back, get back\nI wanna get back, get back with you\nGet back, yeah!\n\n[Talking: Demi Lovato]\nThank you so much!\nI love you too!\nThank you guys so much!\nIt's so sweet!\nI love you guys so much!\nGive it up for my band!\nThank you!", "image": "https://images.genius.com/5d0dbbab5905922fbefcd714b734c886.500x500x1.jpg"}], "artist": "Demi Lovato"}