{"songs": [{"title": "Spaceship Coupe", "album": "The 20/20 Experience: The Complete Experience", "year": "2013-03-15", "lyrics": "[Intro]\nHey, yeah, yeah\nHey, I wrote this song for you\nListen\n\n[Verse 1]\nEverybody's looking for the fliest thing to say (Fliest thing to say)\nBut I just want to fly (fly away with you, you, you, you)\nI don't want to be the one to alienate, yeah (Alienate)\nYou see, I'm trying to find an alien in you (you) if it's cool, (Cool)\n\n[Pre-Chorus]\nWe can't take an airplane\nWhere we're going is way too high\nGoing where the day sky turns into night\nI got the windows special tinted for the stars that get too bright\nAnd I saved you a seat, so let's ride\n\n[Chorus]\nHop into my spaceship coupe\nThere's only room for two (me and you)\nAnd with the top down\nWe'll cruise around\nLand and make love on the moon\n(Would you like that?)\nHop into my spaceship coupe\nThere's only room for two (me and you)\nAnd with the top off, you're all wrapped up\nIn my space lover cocoon\n\n[Post-Chorus]\nAnd I love it when I hear you say\nOoh, ooh, ooh, ooh, ooh (Yeah)\nOoh, ooh, ooh, ooh, ooh\nSing to me\nI love it when I hear you say\nOoh, ooh, ooh, ooh, ooh\nOoh, ooh, ooh, ooh, ooh\nSing to me (Yeah)\n\n[Verse 2]\nNow everybody knows that you're from outer space (Outer space)\nBut honey, I just want to turn out this space with you (You, you, you)\nSo drive me to your galaxy where I could play, yeah (That milky way)\nAnd sugar, I'll take my time\nAnd show you the backseat view, (view) if it's cool (Cool)\n\n[Pre-Chorus]\nWe can't take an airplane\nWhere we're going is way too high\nGoing where the day sky turns into night\nI got the windows special tinted for the stars that get too bright\nAnd I saved you a seat, so let's ride\n\n[Chorus 2]\nHop into my spaceship coupe\nThere's only room for two (And that's me and you)\nAnd with the top down\nWe'll cruise around\nLand and make love on the moon\nHop into my spaceship coupe\nThere's only room for two (Me and you)\nAnd with the top off, you're all wrapped up\nIn my space lover cocoon\n\n[Post-Chorus]\nAnd I love it when I hear you say\nOoh, ooh, ooh, ooh, ooh\nOoh, ooh, ooh, ooh, ooh\nSing to me\nI love it when I hear you say\nOoh, ooh, ooh, ooh, ooh\nOoh, ooh, ooh, ooh, ooh\nGo on and sing to me\nNow break it down\n\n[Breakdown]\nHey...\nThis is the part\nWhere you, and me, and all of the stars collide tonight\nThis is the part\nWhere we take off\nAnd then we fly far away, far away, far away\n\n[Chorus]\nHop into my spaceship coupe\nThere's only room for two (Me and you)\nAnd with the top down\nWe'll cruise around\nLand and make love on the moon\nHop into my spaceship coupe\nThere's only room for two (me and you)\nAnd with the top off, you're all wrapped up\nIn my space lover cocoon\n\n[Post-Chorus]\nOoh, ooh, ooh, ooh, ooh\nOoh, ooh, ooh, ooh, ooh\nOoh, ooh, ooh, ooh, ooh\nOoh, ooh, ooh, ooh, ooh\nOoh, ooh, ooh, ooh, ooh\nOoh, ooh, ooh, ooh, ooh\nOoh, ooh, ooh, ooh, ooh\nOoh, ooh, ooh, ooh, ooh\n\n[Outro]\nBaby, can't you see all the stars?\nThey shine, they shine\nJust for you\nI said oh, yeah, yeah\nJust hop into my spaceship coupe\nI saved a seat for you\nRight here next to me\nI'm going to take you to the moon\nAnd I'm going to make you say\nOoh, ooh, ooh, ooh, ooh\nOoh, ooh, ooh, ooh, ooh\nI love it when I hear you say\nOoh, ooh, ooh, ooh, ooh\nOoh, ooh, ooh, ooh, ooh\nAnd you love it when I make you say\nOoh, ooh, ooh, ooh, ooh\nOoh, ooh, ooh, ooh, ooh\nBaby, this is the part\nWhere you, and me, and all of the stars collide tonight\nThis is the part\nWhere we take off\nAnd then we fly far away, far away, far away", "image": "https://images.genius.com/d9a4f8d56b2a7e9b4f94e29a6277ff91.1000x1000x1.jpg"}], "artist": "Justin Timberlake"}