{"songs": [{"title": "The Hard Stuff", "album": "Man of the Woods", "year": "2018-02-02", "lyrics": "[Intro]\nSo give me the hard stuff (hard stuff)\nOohh, yeah\n\n[Verse 1]\nAnybody can be in love on a sunny day\nAnybody can turn and run when it starts to rain\nAnd everybody wishes all the skies were blue\nBut that ain't the kind of love I'm lookin' to have with you\n\n[Chorus]\nSo give me the hard stuff\nThe kind that makes you real\nI'll be there when the storm comes\n'Cause I want the hard stuff\nWhen they're throwin' sticks and stones\nWe can cut each other to the bone\nI'm never gonna give you up\n'Cause I want the hard stuff (hard stuff)\nYeah I want the hard stuff (hard stuff, yeah)\n\n[Verse 2]\nMy god knows I'm not the man that I want to be\nAnd we all know there's things in this life we refuse to see\nSo just know my fire for you will always burn\nAnd please forgive the things in this life that I have to learn\n\n[Chorus]\nSo give me the hard stuff\nThe kind that makes you real\nI wanna be there when the storm comes\n'Cause I want the hard stuff (hard stuff)\nWhen they're throwin' sticks and stones\nWe can cut each other to the bone\nI'm never gonna give you up\n'Cause I want the hard stuff (hard stuff)\n\n[Bridge]\nNo, we won't have to wonder\nOh, you won't have to wonder\nIf we're ever goin' under\nNo, we're never goin' under\nNo, we're never goin' under\n\n[Chorus]\n'Cause I want the hard stuff\nThe kind that makes you real\nI wanna be there when the storm comes\n'Cause I want the hard stuff (I want the hard stuff)\nWhen they're throwin' sticks and stones\nCut each other to the bone (break each other to the bone)\nI'm never gonna give you up\n'Cause I want the hard stuff (hard stuff, oh)\nYeah I want the hard stuff (I want the hard stuff)\n\n[Outro]\nYeah I want the hard stuff\nGive me the hard stuff\nGive me the hard stuff\nYeah I want the hard stuff\nSo give me the hard stuff", "image": "https://images.genius.com/1c8e917da0dbd0655efbd89cbc806d9d.1000x1000x1.jpg"}], "artist": "Justin Timberlake"}