{"songs": [{"title": "Are We All We Are", "album": "The Truth About Love", "year": "2013-10-31", "lyrics": "[Intro]\nAre we all we are\nAre we all we are\n\n[Verse 1]\nCut to now, holy wow\nWhen did everything become such a hell of a mess?\nMaybe now, maybe now, can somebody come and take this off my chest?\nI know you think it's not your problem\nI know you think that God will solve them\nBut if your shit is not together\nIt'll never be you and me, plant the seed\nOpen up and let it be\n\n[Chorus]\nWe are the people that you'll never get the best of\nNot forget the rest of, rest of (Ooh)\nWe've had our fill, we've had enough, we've had it up here\nAre we all we are\nAre we all we are\nWe are the people that you'll never get the best of\nNot forget the rest of, rest of (Ooh)\nJust sing it loud, until the kids will sing it right back\nAre we all we are\nAre we all we are (Ooh)\nAre we all we are\nAre we all we are\n\n[Verse 2]\nSeven seconds, seven seconds\nThat is all the time you got to make your point\nMy attention, my attention's like an infant tryna crawl around this joint\nI know we're better than the masses\nBut we're all following our asses\nAnd if our shit is not together\nIt'll never be you and me, plant the seed\nOpen and let it be\n\n[Chorus]\nWe are the people that you'll never get the best of\nNot forget the rest of, rest of (Ooh)\nWe've had our fill, we've had enough, we've had it up here\nAre we all we are\nAre we all we are\nWe are the people that you'll never get the best of\nNot forget the rest of, rest of (Ooh)\nJust sing it loud, until the kids will sing it right back\nAre we all we are\nAre we all we are\n\n[Bridge]\nFour, that's how many years it took me to get through the lesson\nThat I had to do it all on my own\nThree, that's how many Hail Mary's they would pray for me\nThinking I was gonna end up all alone\nTwo for second chances that you've given me\nCan it be, lucky me, lucky me, now let's go\nOne, it's what we are, it's what we are\nAre we all we are\nAre we all we are\n\n[Chorus]\nWe are the people that you'll never get the best of\nNot forget the rest of, rest of (Ooh)\nWe've had our fill, we've had enough, we've had it up here\nAre we all we are\nAre we all we are\nWe are the people that you'll never get the best of\nNot forget the rest of, rest of (Ooh)\nJust sing it loud, until the kids will sing it right back\nAre we all we are\nAre we all we are\nWe are the people that you'll never get the best of\nNot forget the rest of, rest of (Ooh)\nWe've had our fill, we've had enough, we've had it up here\nAre we all we are\nAre we all we are\nWe are the people that you'll never get the best of\nNot forget the rest of, rest of (Ooh)\nCut to the future, sing it loud, and take the power back\nAre we all we are\nAre we all we are", "image": "https://images.genius.com/4ded520e62135c9290808fe058738884.1000x1000x1.jpg"}], "artist": "P!nk"}