{"songs": [{"title": "California Dreamin\u2019", "album": "San Andreas Original Motion Pictures Soundtrack", "year": "2015-05-12", "lyrics": "[Verse 1]\nAll the leaves are brown and the sky is gray\nI've been for a walk on a winter's day\nI'd be safe and warm if I was in L.A.\nCalifornia dreamin', oh, on such a winter's day\nAll the leaves are brown and the sky is gray\nI've been for a walk on a winter's day\nI'd be safe and warm if I was in L.A.\nOh, California dreamin', on such a winter's day\n\n[Verse 2]\nI stopped into a church I passed along the way\nWell, I got down on my knees\nAnd I pretended to pray\nYou know the preacher likes the cold\nHe knows I'm gonna stay\nCalifornia dreamin', oh, oh, on such a winter's day\n\n[Breakdown]\nI'd be safe and warm\nI'd be safe and warm\nI'd be safe and warm\nI'd be safe and warm\n\n[Outro]\nAll the leaves are brown (all the leaves are brown)\nAnd the sky is gray (and the sky is gray)\nI've been for a walk, oh, on a winter's day\nIf I didn't go, I could leave today\nCalifornia dreamin', on such a winter's day\nOh, on such a winter's day\nOn such a winter's day", "image": "https://images.rapgenius.com/1b5bd4374579a9388e43636b0cc04efc.450x450x1.jpg"}], "artist": "Sia"}