{"songs": [{"title": "\u200bbitches broken hearts", "album": "dont smile at me (Japanese Import)", "year": "2018-03-30", "lyrics": "[Chorus]\nYou can pretend you don't miss me (Me)\nYou can pretend you don't care\nAll you wanna do is kiss me (Me)\nOh, what a shame, I'm not there\nYou can pretend you don't miss me (Me)\nYou can pretend you don't care\nAll you wanna do is kiss me (Me)\nWell, what a shame, I'm not there\n\n[Verse 1]\nWhat is it you want?\nYou can lie, but I know that you're not fine\nEvery time you talk\nIt's all 'bout me, but you swear I'm not on your mind\n\n[Chorus]\nYou can pretend you don't miss me (Me)\nYou can pretend you don't care\nAll you wanna do is kiss me (Me)\nOh, what a shame, I'm not there\n\n[Verse 2]\nEverybody knows\nYou and I are suicide and stolen art (Art)\nPretty mama sews\nStitches into all your bitches broken hearts\n\n[Chorus]\nYou can pretend you don't miss me (Me)\nYou can pretend you don't care\nAll you wanna do is kiss me (Me)\nOh, what a shame, I'm not there\n\n[Bridge]\nSomebody new is gonna comfort you\nLike you want me to\nSomebody new is gonna comfort me\nLike you never do\n\n[Outro]\nEvery now and then, it hits me\nThat I'm the one that got away\nBut I guess being lonely fits me\nAnd you were made for begging, \"stay\"", "image": "https://images.genius.com/773c0143a6572a0bc07ad81b9d640406.640x640x1.jpg"}], "artist": "Billie Eilish"}