{"songs": [{"title": "\u200bwish you were gay", "album": "WHEN WE ALL FALL ASLEEP, WHERE DO WE GO? (Japanese Import)", "year": "2019-03-04", "lyrics": "[Verse 1]\n\"Baby, I don't feel so good,\" six words you never understood\n\"I'll never let you go,\" five words you'll never say (Aww)\nI laugh along like nothing's wrong, four days has never felt so long\nIf three's a crowd and two was us, one slipped away (Hahahahahahahaha)\n\n[Chorus]\nI just wanna make you feel okay\nBut all you do is look the other way\nI can't tell you how much I wish I didn't wanna stay\nI just kinda wish you were gay\n\n[Verse 2]\nIs there a reason we're not through?\nIs there a 12 step just for you?\nOur conversation's all in blue\n11 \"heys\" (Hey, hey, hey, hey)\nTen fingers tearin' out my hair\nNine times you never made it there\nI ate alone at 7, you were six minutes away\n(Yay)\n\n[Chorus]\nHow am I supposed to make you feel okay\nWhen all you do is walk the other way?\nI can't tell you how much I wish I didn't wanna stay\nI just kinda wish you were gay\n\n[Bridge]\nTo spare my pride\nTo give your lack of interest an explanation\nDon't say I'm not your type\nJust say that I'm not your preferred sexual orientation\nI'm so selfish\nBut you make me feel helpless, yeah\nAnd I can't stand another day\nStand another day\n\n[Chorus]\nI just wanna make you feel okay\nBut all you do is look the other way, hmm\nI can't tell you how much I wish I didn't wanna stay\nI just kinda wish you were gay\nI just kinda wish you were gay\nI just kinda wish you were gay", "image": "https://images.genius.com/ef2bfc01092b457263dab4dcff8ce61b.939x939x1.jpg"}], "artist": "Billie Eilish"}