{"songs": [{"title": "Baby, It\u2019s Cold Outside", "album": "Wrapped in Red", "year": "2013-10-25", "lyrics": "[Verse 1: Kelly Clarkson (w/ Ronnie Dunn)]\nI really can't stay\n(Baby, it's cold outside)\nI've got to go away\n(Baby, it's cold outside)\nThis evening has been so very nice\n(Been hoping that you'd drop by\nI'll hold your hands they're just like ice)\nMy mother will start to worry\n(Beautiful, what's your hurry?)\nMy father will be pacing the floor\n(Listen to the fireplace roar)\nSo really I'd better scurry\n(Beautiful, please don't hurry)\nOh, maybe just a half a drink more\n(Put some records on while I pour)\nThe neighbors might think\n(Oh, it's bad out there)\nSay, what's in this drink\n(No cabs to be had out there)\nI wish I knew how to break the spell\n(Your eyes are like starlight now\nI'll take your hat, your hair looks swell)\nI ought to say no, no, no, sir\n(Mind if I move a little closer?)\nAt least I'm gonna say that I tried\n(What's the use in hurting my pride?)\nI really can't stay\n(Baby don't hold out)\nOh, but it's cold outside (Oh, but it's cold outside)\n\n[Piano Solo]\n\n[Verse 2: Kelly Clarkson (w/ Ronnie Dunn)]\nI simply must go\n(Baby, it's cold outside)\nThe answer is no\n(Baby, it's cold outside)\nYour welcome has been so nice and warm\n(Baby, it's cold outside\nLook out the window at that storm)\nMy sister will be suspicious\n(Gosh, your lips look delicious)\nMy brother will be there at the door\n(Waves upon a tropical shore)\nMy maiden aunt's mind is vicious\n(Your lips are delicious)\nWell, maybe just a cigarette more\n(Never such a blizzard before)\nI've got to get home\n(Baby, you'll freeze out there)\nSay, lend me your coat\n(It's up to your knees out there)\nYou've really been grand\n(I'm thrilled when you touch my hand)\nBut don't you see\n(How can you do this to me?)\nThere's bound to be talk tomorrow\n(Think about my life long sorrow)\nAt least there'll be plenty advised\n(If you caught pneumonia and died)\nI really can't stay\n(Get over that old out)\nBut it's cold outside (But it's cold outside)", "image": "https://images.genius.com/c777d58e6d67da03413c106c0f3d0445.1000x1000x1.jpg"}], "artist": "Kelly Clarkson"}