{"songs": [{"title": "Curious (Sweater Beats Remix)", "album": null, "year": "2018-03-09", "lyrics": "[Intro]\nI'm just curious\nI'm just curious\n\n[Verse 1]\nI need a drink, whiskey ain't my thing\nBut shit is all good\nI can handle things like I wish that you would\nYou've been out of reach, could you explain?\nI think that you should\nWhat you been up to?\nWho's been loving you good?\n\n[Pre-Chorus]\nI'm just on the floor, I'm like a model\nBeen looking through the texts and all the photos\nBut don't you worry, I can handle it\nNo, don't you worry, I can handle it\n\n[Chorus]\nI'm just curious (I'm, I'm, I'm...)\nI'm just curious (I'm, I'm, I'm...)\nI'm just curious (I'm, I'm, I'm...)\nI'm just curious (I'm, I'm, I'm...)\n\n[Verse 2]\nCalling me up, so late at night\nAre we just friends?\nYou say you wanted me, but you're sleeping with him\nYou think of me, I'm what you see\nWhen you look at the sky\nI don't believe you\nYou ain't been loving me right, yeah\n\n[Pre-Chorus]\nI'm just on the floor, I'm like a model, yeah\nBeen looking through the texts and all the photos\nBut don't you worry I can handle it\nNo, don't you worry I can handle it\n\n[Chorus]\nI'm just curious (I'm, I'm, I'm...)\nI'm just curious (I'm, I'm, I'm...)\nI'm just curious (I'm, I'm, I'm...)\nI'm just curious\n\n[Bridge]\nTouch ya, touch ya, touch ya, touch ya, touch ya\nIf you let him touch ya, touch ya, touch ya, touch ya\nYou let used to, used to, used to, used to, used to\nUsed to, used to, used to, used to, used to\nTouch ya, touch ya, touch ya, touch ya, touch ya\nIf you let him touch ya, touch ya, touch ya, touch ya\nYou let used to, used to, used to, used to, used to\nUsed to, used to, used to, used to, used to\n\n[Chorus 2]\n(I'm just, I'm just)\nI'm just curious\nI'm just curious\nI'm just, I'm just curious", "image": "https://images.genius.com/c40b2c265e6331fd27be2e2ef32a8329.1000x1000x1.png"}], "artist": "Hayley Kiyoko"}