{"songs": [{"title": "Clocks", "album": "A Rush of Blood to the Head", "year": "2002-08-26", "lyrics": "[Verse 1]\nThe lights go out and I can't be saved\nTides that I tried to swim against\nHave brought me down upon my knees\nOh I beg, I beg and plead, singing\n\nCome out of things unsaid\nShoot an apple off my head and a\nTrouble that can't be named\nA tiger's waiting to be tamed, singing\u2014\n\n[Chorus]\nYou are\nYou are\n\n[Verse 2]\nConfusion never stops\nClosing walls and ticking clocks, gonna\nCome back and take you home\nI could not stop that you now know, singin'\n\nCome out upon my seas\nCursed missed opportunities, am I\nA part of the cure?\nOr am I part of the disease? Singing\u2014\n\n[Chorus]\nYou are\nYou are\nYou are\nYou are(5381091)\n\nYou are\nYou are\n\n[Bridge]\nAnd nothing else compares\nOh nothing else compares\nAnd nothing else compares\n\n[Piano hook]\n\n[Chorus]\nYou are\nYou are\n\nHome, home\nWhere I wanted to go\nHome, home\nWhere I wanted to go\nHome, (you) home\nWhere I wanted to (are) go\nHome, home\nWhere I wanted to go", "image": "https://images.genius.com/397914c2e2cf6ba047c4d88ef1e44250.1000x1000x1.png"}], "artist": "Coldplay"}