{"songs": [{"title": "Kaleidoscope", "album": "A Head Full of Dreams", "year": "2015-12-04", "lyrics": "[Instrumental Break]\n\n[Verse: Coleman Barks]\nThis being human is a guest house\nEvery morning a new arrival\nA joy, a depression, a meanness\nSome momentary awareness comes\nAs an unexpected visitor\nWelcome and entertain them all!\nBe grateful for whoever comes\nBecause each has been sent as a guide\n\n[Outro]", "image": "https://images.genius.com/12d516032282bfc5b71a772bbc1090de.640x640x1.jpg"}], "artist": "Coldplay"}